manim_slides/__init__.py
manim_slides/__main__.py
manim_slides/__version__.py
manim_slides/checkhealth.py
manim_slides/commons.py
manim_slides/config.py
manim_slides/convert.py
manim_slides/defaults.py
manim_slides/logger.py
manim_slides/py.typed
manim_slides/qt_utils.py
manim_slides/render.py
manim_slides/resources.py
manim_slides/utils.py
manim_slides/docs/__init__.py
manim_slides/docs/manim_slides_directive.py
manim_slides/ipython/ipython_magic.py
manim_slides/present/__init__.py
manim_slides/present/player.py
manim_slides/slide/__init__.py
manim_slides/slide/animation.py
manim_slides/slide/base.py
manim_slides/slide/manim.py
manim_slides/slide/manimlib.py
manim_slides/templates/__init__.py
manim_slides/templates/revealjs.html
manim_slides/wizard/__init__.py
manim_slides/wizard/wizard.py
manim_slides-5.5.3.dist-info/METADATA
manim_slides-5.5.3.dist-info/WHEEL
manim_slides-5.5.3.dist-info/entry_points.txt
manim_slides-5.5.3.dist-info/licenses/LICENSE.md
manim_slides-5.5.3.dist-info/RECORD
