Metadata-Version: 2.4
Name: manim-slides
Version: 5.5.3
Summary: Tool for live presentations using manim
Project-URL: Changelog, https://github.com/jeertmans/manim-slides/releases
Project-URL: Documentation, https://eertmans.be/manim-slides
Project-URL: Founding, https://github.com/sponsors/jeertmans
Project-URL: Homepage, https://github.com/jeertmans/manim-slides
Project-URL: Repository, https://github.com/jeertmans/manim-slides
Author-email: Jérome Eertmans <jeertmans@icloud.com>
License-Expression: MIT
License-File: LICENSE.md
Keywords: manim,manimgl,plugin,slides
Classifier: License :: OSI Approved :: MIT License
Classifier: Operating System :: OS Independent
Classifier: Programming Language :: Python :: 3
Classifier: Programming Language :: Python :: 3.9
Classifier: Programming Language :: Python :: 3.10
Classifier: Programming Language :: Python :: 3.11
Classifier: Programming Language :: Python :: 3.12
Classifier: Topic :: Multimedia :: Graphics
Classifier: Topic :: Multimedia :: Video
Classifier: Topic :: Scientific/Engineering
Requires-Python: >=3.9
Requires-Dist: av<14,>=9.0.0
Requires-Dist: beautifulsoup4>=4.12.3
Requires-Dist: click-default-group>=1.2.2
Requires-Dist: click>=8.1.3
Requires-Dist: jinja2>=3.1.2
Requires-Dist: lxml>=4.9.2
Requires-Dist: numpy>=1.19
Requires-Dist: pillow>=9.5.0
Requires-Dist: pydantic-extra-types>=2.0.0
Requires-Dist: pydantic>=2.0.1
Requires-Dist: python-pptx>=0.6.21
Requires-Dist: qtpy>=2.4.1
Requires-Dist: requests>=2.28.1
Requires-Dist: rich>=13.3.2
Requires-Dist: rtoml>=0.11.0
Requires-Dist: tqdm>=4.64.1
Provides-Extra: full
Requires-Dist: docutils>=0.20.1; extra == 'full'
Requires-Dist: ipython>=8.12.2; extra == 'full'
Requires-Dist: manim>=0.19; extra == 'full'
Provides-Extra: magic
Requires-Dist: ipython>=8.12.2; extra == 'magic'
Requires-Dist: manim>=0.19; extra == 'magic'
Provides-Extra: manim
Requires-Dist: manim>=0.19; extra == 'manim'
Provides-Extra: manimgl
Requires-Dist: manimgl>=1.7.2; extra == 'manimgl'
Requires-Dist: setuptools<81; extra == 'manimgl'
Provides-Extra: pyqt6
Requires-Dist: pyqt6>=6.7.0; extra == 'pyqt6'
Provides-Extra: pyqt6-full
Requires-Dist: docutils>=0.20.1; extra == 'pyqt6-full'
Requires-Dist: ipython>=8.12.2; extra == 'pyqt6-full'
Requires-Dist: manim>=0.19; extra == 'pyqt6-full'
Requires-Dist: pyqt6>=6.7.0; extra == 'pyqt6-full'
Provides-Extra: pyside6
Requires-Dist: pyside6!=6.8.1.1,>=6.6.1; extra == 'pyside6'
Provides-Extra: pyside6-full
Requires-Dist: docutils>=0.20.1; extra == 'pyside6-full'
Requires-Dist: ipython>=8.12.2; extra == 'pyside6-full'
Requires-Dist: manim>=0.19; extra == 'pyside6-full'
Requires-Dist: pyside6!=6.8.1.1,>=6.6.1; extra == 'pyside6-full'
Provides-Extra: sphinx-directive
Requires-Dist: docutils>=0.20.1; extra == 'sphinx-directive'
Requires-Dist: manim>=0.19; extra == 'sphinx-directive'
